venv_tools/_utils.py
venv_tools/_venv_builders.py
venv_tools/__init__.py
venv_tools-0.1.dist-info/metadata.json
venv_tools-0.1.dist-info/RECORD
venv_tools-0.1.dist-info/WHEEL
venv_tools-0.1.dist-info/top_level.txt
venv_tools-0.1.dist-info/LICENSE.txt
venv_tools-0.1.dist-info/METADATA
venv_tools-0.1.dist-info/DESCRIPTION.rst
