Metadata-Version: 2.0
Name: venv-tools
Version: 0.1
Summary: A bunch of tools for using venvs (and virtualenvs) from python.
Home-page: http://venv_tools.rtfd.org
Author: James Tocknell
Author-email: aragilar@gmail.com
License: BSD
Keywords: virtualenv venv
Platform: UNKNOWN
Classifier: Development Status :: 3 - Alpha
Classifier: Intended Audience :: Developers
Classifier: Topic :: Software Development :: Libraries :: Python Modules
Classifier: Topic :: System :: Shells
Classifier: License :: OSI Approved :: BSD License
Classifier: Programming Language :: Python :: 2
Classifier: Programming Language :: Python :: 2.6
Classifier: Programming Language :: Python :: 2.7
Classifier: Programming Language :: Python :: 3
Classifier: Programming Language :: Python :: 3.1
Classifier: Programming Language :: Python :: 3.2
Classifier: Programming Language :: Python :: 3.3
Provides-Extra: virtualenv
Requires-Dist: virtualenv; python_version < '3.3' or extra == "virtualenv"
